nlogger/__init__.py
nlogger/nlogger.py
nlogger-1b0.dist-info/LICENSE.txt
nlogger-1b0.dist-info/METADATA
nlogger-1b0.dist-info/WHEEL
nlogger-1b0.dist-info/top_level.txt
nlogger-1b0.dist-info/RECORD
