Metadata-Version: 2.1
Name: nlogger
Version: 1b0
Summary: Package to use NLogger web service to send notification and logs to mobile devices.
Home-page: UNKNOWN
Author: Balaviknesh Sekar
Author-email: bala21karthick@gmail.com
License: MIT
Download-URL: https://pypi.org/project/nlogger/
Keywords: NLogger,Notifications,Logs,SmartPhones,iOS,Android
Platform: UNKNOWN
Requires-Dist: requests
